TensorClus/__init__.py
TensorClus/initialization.py
TensorClus/testTensorClus.py
TensorClus/coclustering/__init__.py
TensorClus/coclustering/baseDiagonalCoclustering.py
TensorClus/coclustering/baseNonDiagonalCoclustering.py
TensorClus/coclustering/sliceMatrixCoclustering.py
TensorClus/coclustering/sparseTensorCoclustering.py
TensorClus/coclustering/tensorCoclusteringBernoulli.py
TensorClus/coclustering/tensorCoclusteringGaussian.py
TensorClus/coclustering/tensorCoclusteringPoisson.py
TensorClus/decomposition/__init__.py
TensorClus/decomposition/decomposition_with_clustering.py
TensorClus/reader/__init__.py
TensorClus/reader/load.py
TensorClus/tests/__init__.py
TensorClus/tests/input_checking.py
TensorClus/vizualisation/__init__.py
TensorClus-0.0.2.dist-info/LICENSE
TensorClus-0.0.2.dist-info/METADATA
TensorClus-0.0.2.dist-info/WHEEL
TensorClus-0.0.2.dist-info/top_level.txt
TensorClus-0.0.2.dist-info/RECORD
