Metadata-Version: 2.1
Name: TensorClus
Version: 0.0.2
Summary: TensorClus is a Python package for clustering of three-way tensor data
Home-page: https://github.com/boutalbi/TensorClus
Author: Rafika Boutalbi,Mohamed Nadif, Lazhar Labiod
Author-email: boutalbi.rafika@gmail.com
License: BSD 3-Clause License
Project-URL: Bug Tracker, https://github.com/boutalbi/TensorClus/issues
Keywords: Tensor Clustering framework
Platform: *nix
Classifier: Programming Language :: Python :: 3
Classifier: License :: OSI Approved :: BSD License
Classifier: Operating System :: OS Independent
Requires-Dist: pip (>=19.0)
Requires-Dist: numpy (==1.17.4)
Requires-Dist: pandas (==1.0.3)
Requires-Dist: scipy (==1.2.1)
Requires-Dist: scikit-learn (==0.22.1)
Requires-Dist: matplotlib (==3.1.3)
Requires-Dist: coclust
Provides-Extra: alldeps
Requires-Dist: numpy (==1.17.4) ; extra == 'alldeps'
Requires-Dist: pandas (==1.0.3) ; extra == 'alldeps'
Requires-Dist: scipy (==1.2.1) ; extra == 'alldeps'
Requires-Dist: scikit-learn (==0.22.1) ; extra == 'alldeps'
Requires-Dist: matplotlib (==3.1.3) ; extra == 'alldeps'
Requires-Dist: coclust ; extra == 'alldeps'
Requires-Dist: tensorly ; extra == 'alldeps'
